Metadata-Version: 2.4
Name: mcp-server-deepresearch-20250617
Version: 0.1.0
Summary: 实现类deepresearch功能的MCP工具
Requires-Python: >=3.10
Requires-Dist: asyncio>=3.4.3
Requires-Dist: build>=1.2.2.post1
Requires-Dist: mcp>=1.9.4
Requires-Dist: openai>=1.88.0
Requires-Dist: openai-agents>=0.0.18
Requires-Dist: pydantic>=2.11.7
Requires-Dist: twine>=6.1.0
Requires-Dist: typing>=3.10.0.0
